edc_dx_review/__init__.py
edc_dx_review/apps.py
edc_dx_review/auth_objects.py
edc_dx_review/auths.py
edc_dx_review/choices.py
edc_dx_review/constants.py
edc_dx_review/fieldsets.py
edc_dx_review/list_data.py
edc_dx_review/medical_date.py
edc_dx_review/models.py
edc_dx_review/radio_fields.py
edc_dx_review/utils.py
edc_dx_review/form_mixins/__init__.py
edc_dx_review/form_mixins/clinical_review_baseline_required_form_mixin.py
edc_dx_review/form_validator_mixins/__init__.py
edc_dx_review/form_validator_mixins/clinical_review_baseline_form_validator_mixin.py
edc_dx_review/form_validator_mixins/clinical_review_followup_form_validator_mixin.py
edc_dx_review/migrations/0001_initial.py
edc_dx_review/migrations/0002_diagnosislocations_extra_value_and_more.py
edc_dx_review/migrations/0003_alter_diagnosislocations_options_and_more.py
edc_dx_review/migrations/0004_remove_diagnosislocations_edc_dx_revi_name_a39b40_idx_and_more.py
edc_dx_review/migrations/__init__.py
edc_dx_review/model_mixins/__init__.py
edc_dx_review/model_mixins/clinical_review_baseline_model_mixin.py
edc_dx_review/model_mixins/dx_location_model_mixin.py
edc_dx_review/model_mixins/clinical_review_followup/__init__.py
edc_dx_review/model_mixins/clinical_review_followup/clinical_review_followup_chol_model_mixin.py
edc_dx_review/model_mixins/clinical_review_followup/clinical_review_followup_dm_model_mixin.py
edc_dx_review/model_mixins/clinical_review_followup/clinical_review_followup_hiv_model_mixin.py
edc_dx_review/model_mixins/clinical_review_followup/clinical_review_followup_htn_model_mixin.py
edc_dx_review/model_mixins/clinical_review_followup/clinical_review_followup_model_mixin.py
edc_dx_review/model_mixins/factory/__init__.py
edc_dx_review/model_mixins/factory/baseline_review_model_mixin_factory.py
edc_dx_review/model_mixins/factory/calculate_date.py
edc_dx_review/model_mixins/factory/dx_initial_review_model_mixin_factory.py
edc_dx_review/model_mixins/factory/followup_review_model_mixin_factory.py
edc_dx_review-1.0.1.dist-info/AUTHORS
edc_dx_review-1.0.1.dist-info/LICENSE
edc_dx_review-1.0.1.dist-info/METADATA
edc_dx_review-1.0.1.dist-info/WHEEL
edc_dx_review-1.0.1.dist-info/top_level.txt
edc_dx_review-1.0.1.dist-info/RECORD
